ocla/__init__.py
ocla/cli.py
ocla/cli_io.py
ocla/config.py
ocla/session.py
ocla/state.py
ocla/util.py
ocla/providers/__init__.py
ocla/providers/ollama_provider.py
ocla/providers/openai_provider.py
ocla/tools/__init__.py
ocla/tools/file_system.py
ocla/tools/git.py
ocla-0.1.3.dist-info/licenses/LICENSE
ocla-0.1.3.dist-info/METADATA
ocla-0.1.3.dist-info/WHEEL
ocla-0.1.3.dist-info/entry_points.txt
ocla-0.1.3.dist-info/top_level.txt
ocla-0.1.3.dist-info/RECORD
