Metadata-Version: 2.4
Name: ocla
Version: 0.1.3
Summary: CLI coding agent with Ollama support
Author-email: Vaeryn <dev@vaeryn.co.uk>
License-Expression: MIT
Project-URL: Repository, https://github.com/vaeryn-uk/ollama-cli-code-agent
Requires-Python: >=3.9
License-File: LICENSE
Requires-Dist: ollama
Requires-Dist: openai
Requires-Dist: humanize
Requires-Dist: rich
Requires-Dist: tzlocal
Requires-Dist: GitPython
Requires-Dist: tiktoken
Provides-Extra: test
Requires-Dist: pytest; extra == "test"
Provides-Extra: dev
Requires-Dist: black; extra == "dev"
Dynamic: license-file
